odoo/addons/product_configurator_stock/README.rst
odoo/addons/product_configurator_stock/__init__.py
odoo/addons/product_configurator_stock/__manifest__.py
odoo/addons/product_configurator_stock/data/menu_product.xml
odoo/addons/product_configurator_stock/demo/product_template.xml
odoo/addons/product_configurator_stock/i18n/product_configurator_stock.pot
odoo/addons/product_configurator_stock/models/__init__.py
odoo/addons/product_configurator_stock/models/stock_move.py
odoo/addons/product_configurator_stock/models/stock_picking.py
odoo/addons/product_configurator_stock/readme/DESCRIPTION.rst
odoo/addons/product_configurator_stock/readme/USAGE.rst
odoo/addons/product_configurator_stock/security/ir.model.access.csv
odoo/addons/product_configurator_stock/static/description/icon.png
odoo/addons/product_configurator_stock/static/description/index.html
odoo/addons/product_configurator_stock/tests/__init__.py
odoo/addons/product_configurator_stock/tests/test_stock.py
odoo/addons/product_configurator_stock/views/product_view.xml
odoo/addons/product_configurator_stock/views/stock_move_view.xml
odoo/addons/product_configurator_stock/views/stock_picking_view.xml
odoo/addons/product_configurator_stock/wizard/__init__.py
odoo/addons/product_configurator_stock/wizard/product_configurator.py
odoo14_addon_product_configurator_stock-14.0.1.1.0.dist-info/METADATA
odoo14_addon_product_configurator_stock-14.0.1.1.0.dist-info/WHEEL
odoo14_addon_product_configurator_stock-14.0.1.1.0.dist-info/top_level.txt
odoo14_addon_product_configurator_stock-14.0.1.1.0.dist-info/RECORD
